Metadata-Version: 2.4
Name: tech-shrimp-mcp-demo
Version: 0.1.0
Summary: Add your description here
Author-email: tech-shrimp <techshrimp@163.com>
Requires-Python: >=3.13
Requires-Dist: mcp[cli]>=1.9.2
